assetic_esri/__init__.py
assetic_esri/__version__.py
assetic_esri/config.py
assetic_esri/initialise.py
assetic_esri/settings/__init__.py
assetic_esri/settings/assetic_esri_config.py
assetic_esri/tools/__init__.py
assetic_esri/tools/dummy_process_dialog.py
assetic_esri/tools/esri_layertools.py
assetic_esri/tools/esri_messager.py
assetic_esri/tools/legacy_commontools.py
assetic_esri/tools/legacy_layertools.py
assetic_esri/tools/static_def/__init__.py
assetic_esri/tools/static_def/cust_config_xml_defs.py
assetic_esri-1.3.0.4.dist-info/LICENSE.txt
assetic_esri-1.3.0.4.dist-info/METADATA
assetic_esri-1.3.0.4.dist-info/WHEEL
assetic_esri-1.3.0.4.dist-info/top_level.txt
assetic_esri-1.3.0.4.dist-info/RECORD
