Metadata-Version: 2.1
Name: assetic_esri
Version: 1.3.0.4
Summary: Assetic ESRI Integration API
Home-page: http://www.assetic.com
Author-email: developer@assetic.com
Keywords: Assetic ESRI Integration APIs
License-File: LICENSE.txt
Requires-Dist: assetic >=2023.16.1.3
Requires-Dist: arcgis2geojson
Requires-Dist: pandas >=0.12.0
Requires-Dist: six
Requires-Dist: typing
